private_attribute.py
private_attribute-2.8.0.dist-info/METADATA
private_attribute-2.8.0.dist-info/WHEEL
private_attribute-2.8.0.dist-info/RECORD
