Metadata-Version: 2.4
Name: private_attribute
Version: 2.8.0
Summary: Private attribute decorator for Python classes
Project-URL: homepage, https://github.com/Locked-chess-official/private-attribute
Author-email: Locked-chess-official <13140752715@163.com>
License: MIT
